Workbook

Sheet How to use
A2: ZenBudget
A3: The finance planner that fits on one screen.
A6: 1. Start in 'Monthly Budget' — set your planned amount per category.
A7: 2. Log every expense in 'Transactions' as it happens.
A8: 3. Fill in the 'Actual' column in 'Monthly Budget' at the end of the month
A9: (or use =SUMIF('Transactions'!C:C, category, 'Transactions'!E:E) to automate it).
A10: 4. Check 'Dashboard' any time for your savings rate and spending breakdown.
A11: 5. Track goals in 'Savings Goals' and debts in 'Debt Payoff'.
A12: 6. Review 'Subscriptions' monthly — this tab alone usually pays for the planner.
A13: 7. At year end, fill in 'Yearly Overview' for the full 12-month picture.
A15: Tip: duplicate the 'Monthly Budget' tab each month if you want a full history.

Sheet Dashboard
A2: ZenBudget
A3: Your finances, on one page.
A5: Monthly income (from Transactions) | B5: =SUMIF(Transactions!D:D,"Income",Transactions!E:E)
A6: Monthly expenses (planned) | B6: =SUM('Monthly Budget'!C4:C16)
A7: Monthly expenses (actual, from Transactions) | B7: =SUMIF(Transactions!D:D,"Expense",Transactions!E:E)
A8: Savings rate | B8: =IFERROR((B5-B7)/B5,0)
A11: Top expense categories this month
A12: Category | B12: Actual
A13: Housing (rent/mortgage) | B13: ='Monthly Budget'!E4
A14: Utilities | B14: ='Monthly Budget'!E5
A15: Groceries | B15: ='Monthly Budget'!E6
A16: Transport | B16: ='Monthly Budget'!E7
A17: Insurance | B17: ='Monthly Budget'!E8
A18: Debt payments | B18: ='Monthly Budget'!E9
A19: Subscriptions | B19: ='Monthly Budget'!E10
A20: Health | B20: ='Monthly Budget'!E11
A21: Entertainment | B21: ='Monthly Budget'!E12
A22: Shopping | B22: ='Monthly Budget'!E13
A23: Dining out | B23: ='Monthly Budget'!E14
A24: Savings/Investing | B24: ='Monthly Budget'!E15
A25: Other | B25: ='Monthly Budget'!E16

Sheet Monthly Budget
A1: Monthly Budget
A2: Plan vs. actual, by category.
A3: Category | C3: Planned | D3: Actual | E3: Difference
A4: Housing (rent/mortgage) | C4: 0 | D4: 0 | E4: =C4-D4
A5: Utilities | C5: 0 | D5: 0 | E5: =C5-D5
A6: Groceries | C6: 0 | D6: 0 | E6: =C6-D6
A7: Transport | C7: 0 | D7: 0 | E7: =C7-D7
A8: Insurance | C8: 0 | D8: 0 | E8: =C8-D8
A9: Debt payments | C9: 0 | D9: 0 | E9: =C9-D9
A10: Subscriptions | C10: 0 | D10: 0 | E10: =C10-D10
A11: Health | C11: 0 | D11: 0 | E11: =C11-D11
A12: Entertainment | C12: 0 | D12: 0 | E12: =C12-D12
A13: Shopping | C13: 0 | D13: 0 | E13: =C13-D13
A14: Dining out | C14: 0 | D14: 0 | E14: =C14-D14
A15: Savings/Investing | C15: 0 | D15: 0 | E15: =C15-D15
A16: Other | C16: 0 | D16: 0 | E16: =C16-D16
A17: TOTAL | C17: =SUM(C4:C16) | D17: =SUM(D4:D16) | E17: =C17-D17

Sheet Transactions
A1: Transactions
A2: Log every expense and income entry here.
A3: Date | B3: Description | C3: Category | D3: Type | E3: Amount

Sheet Savings Goals
A1: Savings Goals
A2: Track progress toward what matters.
A3: Goal | B3: Target amount | C3: Saved so far | D3: Progress | E3: Target date
D4: =IFERROR(C4/B4,0)
D5: =IFERROR(C5/B5,0)
D6: =IFERROR(C6/B6,0)
D7: =IFERROR(C7/B7,0)
D8: =IFERROR(C8/B8,0)
D9: =IFERROR(C9/B9,0)
D10: =IFERROR(C10/B10,0)
D11: =IFERROR(C11/B11,0)
D12: =IFERROR(C12/B12,0)
D13: =IFERROR(C13/B13,0)

Sheet Debt Payoff
A1: Debt Payoff Tracker
A2: See the finish line.
A3: Debt | B3: Balance | C3: Interest rate (APR) | D3: Minimum payment | E3: Months to payoff (est.)
E4: =IFERROR(B4/D4,0)
E5: =IFERROR(B5/D5,0)
E6: =IFERROR(B6/D6,0)
E7: =IFERROR(B7/D7,0)
E8: =IFERROR(B8/D8,0)
E9: =IFERROR(B9/D9,0)
E10: =IFERROR(B10/D10,0)
E11: =IFERROR(B11/D11,0)

Sheet Subscriptions
A1: Subscription Tracker
A2: Find the money leaks.
A3: Service | B3: Monthly cost | C3: Billing cycle | D3: Next charge | E3: Annual cost
E4: =B4*12
E5: =B5*12
E6: =B6*12
E7: =B7*12
E8: =B8*12
E9: =B9*12
E10: =B10*12
E11: =B11*12
E12: =B12*12
E13: =B13*12
E14: =B14*12
E15: =B15*12
... E19: =B19*12
A20: TOTAL ANNUAL COST | E20: =SUM(E4:E19)

Sheet Yearly Overview
A1: Yearly Overview
A2: The 12-month picture.
A3: Month | B3: Income | C3: Expenses | D3: Net savings
A4: January | B4: 0 | C4: 0 | D4: =B4-C4
A5: February | B5: 0 | C5: 0 | D5: =B5-C5
A6: March | B6: 0 | C6: 0 | D6: =B6-C6
A7: April | B7: 0 | C7: 0 | D7: =B7-C7
A8: May | B8: 0 | C8: 0 | D8: =B8-C8
A9: June | B9: 0 | C9: 0 | D9: =B9-C9
A10: July | B10: 0 | C10: 0 | D10: =B10-C10
A11: August | B11: 0 | C11: 0 | D11: =B11-C11
A12: September | B12: 0 | C12: 0 | D12: =B12-C12
A13: October | B13: 0 | C13: 0 | D13: =B13-C13
A14: November | B14: 0 | C14: 0 | D14: =B14-C14
A15: December | B15: 0 | C15: 0 | D15: =B15-C15
